LICENSE.txt
MANIFEST.in
README.md
WHATSNEW.md
setup.py
src/pdef_compiler.egg-info/PKG-INFO
src/pdef_compiler.egg-info/SOURCES.txt
src/pdef_compiler.egg-info/dependency_links.txt
src/pdef_compiler.egg-info/entry_points.txt
src/pdef_compiler.egg-info/requires.txt
src/pdef_compiler.egg-info/top_level.txt
src/pdefc/__init__.py
src/pdefc/cli.py
src/pdefc/compiler.py
src/pdefc/exc.py
src/pdefc/generators.py
src/pdefc/parser.py
src/pdefc/reserved.py
src/pdefc/sources.py
src/pdefc/version.py
src/pdefc/lang/__init__.py
src/pdefc/lang/collects.py
src/pdefc/lang/common.py
src/pdefc/lang/enums.py
src/pdefc/lang/imports.py
src/pdefc/lang/interfaces.py
src/pdefc/lang/messages.py
src/pdefc/lang/modules.py
src/pdefc/lang/packages.py
src/pdefc/lang/references.py
src/pdefc/lang/types.py