Metadata-Version: 1.1
Name: pdef-compiler
Version: 1.2.0
Summary: Pdef compiler
Home-page: http://github.com/pdef/pdef
Author: Ivan Korobkov
Author-email: ivan.korobkov@gmail.com
License: Apache License 2.0
Platform: UNKNOWN
Classifier: Development Status :: 4 - Beta
Classifier: Environment :: Console
Classifier: Intended Audience :: Developers
Classifier: License :: OSI Approved :: Apache Software License
Classifier: Operating System :: OS Independent
Classifier: Programming Language :: Python :: 2.7
Classifier: Topic :: Software Development :: Code Generators
Classifier: Topic :: Software Development :: Compilers
